discord_embed_model/__init__.py
discord_embed_model/formatter.py
discord_embed_model/model.py
discord_embed_model/stateful.py
discord_embed_model/utils.py
discord_embed_model-0.1.3.dist-info/LICENSE
discord_embed_model-0.1.3.dist-info/METADATA
discord_embed_model-0.1.3.dist-info/WHEEL
discord_embed_model-0.1.3.dist-info/top_level.txt
discord_embed_model-0.1.3.dist-info/RECORD
