Metadata-Version: 2.1
Name: discord-embed-model
Version: 0.1.3
Summary: discord.py advanced embeds
Home-page: https://github.com/ZackaryW/discord_embed_model
Author: Zackary W
Classifier: Programming Language :: Python :: 3
Classifier: License :: OSI Approved :: MIT License
Requires-Python: >=3.8
License-File: LICENSE
Requires-Dist: pydantic
Requires-Dist: discord
